qisquick/__init__.py
qisquick/circuits.py
qisquick/dbconfig.py
qisquick/qis_logger.py
qisquick/run_experiment.py
qisquick/statblock.py
qisquick/tools.py
qisquick/transpilertools.py
qisquick-0.0a8.data/data/qisquick_documentation/README.md
qisquick-0.0a8.data/data/qisquick_documentation/qisquick_documentation.pdf
qisquick-0.0a8.dist-info/LICENSE.md
qisquick-0.0a8.dist-info/METADATA
qisquick-0.0a8.dist-info/WHEEL
qisquick-0.0a8.dist-info/top_level.txt
qisquick-0.0a8.dist-info/RECORD
