Metadata-Version: 2.1
Name: qisquick
Version: 0.0a8
Summary: Utility library for automating running and analyzing transpiler experiments with IBM qiskit
Home-page: https://github.com/ParanoydAndroid/qisquick
Author: Brandon K Kamaka
Author-email: brandon.kamaka@gmail.com
License: MIT
Keywords: transpiler,qiskit,quantum
Platform: UNKNOWN
Classifier: Development Status :: 3 - Alpha
Classifier: Intended Audience :: Education
Classifier: Intended Audience :: Science/Research
Classifier: Topic :: Software Development :: Libraries :: Application Frameworks
Classifier: License :: OSI Approved :: MIT License
Classifier: Programming Language :: Python :: 3
Classifier: Environment :: Win32 (MS Windows)
Requires-Python: >=3.6
Requires-Dist: qiskit
Requires-Dist: numpy
Requires-Dist: scipy
